ddd_domain_driven_design/__init__.py
ddd_domain_driven_design/application/dto/generalisation/.gitignore
ddd_domain_driven_design/application/dto/generalisation/.travis.yml
ddd_domain_driven_design/application/dto/generalisation/LICENSE
ddd_domain_driven_design/application/dto/generalisation/README.md
ddd_domain_driven_design/application/dto/generalisation/dto.py
ddd_domain_driven_design/application/dto/generalisation/dtodescriptor.py
ddd_domain_driven_design/application/dto/generalisation/dtometa.py
ddd_domain_driven_design/application/dto/generalisation/type_checker.py
ddd_domain_driven_design/application/observable/observable.py
ddd_domain_driven_design/application/observable/generalisation/interface/observable.py
ddd_domain_driven_design/application/observable/generalisation/interface/observer.py
ddd_domain_driven_design/domain/utils/logger.py
ddd_domain_driven_design/domain/utils/multiton.py
ddd_domain_driven_design/domain/utils/singleton.py
ddd_domain_driven_design/infrastructure/generalisation/exceptions.py
ddd_domain_driven_design/presentation/adapter/commandadapter.py
ddd_domain_driven_design/presentation/adapter/queryadapter.py
ddd_domain_driven_design/presentation/adapter/generalisation/interface/commandadapter.py
ddd_domain_driven_design/presentation/adapter/generalisation/interface/queryadapter.py
ddd_domain_driven_design/presentation/request/generalisation/interface/request.py
ddd_domain_driven_design-0.0.2.dist-info/DESCRIPTION.rst
ddd_domain_driven_design-0.0.2.dist-info/METADATA
ddd_domain_driven_design-0.0.2.dist-info/RECORD
ddd_domain_driven_design-0.0.2.dist-info/WHEEL
ddd_domain_driven_design-0.0.2.dist-info/metadata.json
ddd_domain_driven_design-0.0.2.dist-info/top_level.txt
